MANIFEST.in
setup.py
bell/__init__.py
bell/_compat.py
bell/analyzer.py
bell/api.py
bell/base.py
bell/cli.py
bell/configs.py
bell/events.py
bell/listener.py
bell/logger.py
bell/signals.py
bell/utils.py
bell/webapp.py
bell/hooks/__init__.py
bell/hooks/hipchat.py
bell/res/configs.toml
bell/res/webapp/static/css/bootstrap.min.css
bell/res/webapp/static/css/index.css
bell/res/webapp/static/css/layout.css
bell/res/webapp/static/css/series.css
bell/res/webapp/static/icons/bell.green.png
bell/res/webapp/static/icons/bell.png
bell/res/webapp/static/icons/bell.red.png
bell/res/webapp/static/images/spinner.gif
bell/res/webapp/static/js/bootstrap-typeahead.js
bell/res/webapp/static/js/bootstrap.min.js
bell/res/webapp/static/js/dygraph-combined.js
bell/res/webapp/static/js/index.js
bell/res/webapp/static/js/jquery.1.10.2.min.js
bell/res/webapp/static/js/series.js
bell/res/webapp/static/js/utils.js
bell/res/webapp/templates/help.html
bell/res/webapp/templates/index.html
bell/res/webapp/templates/layout.html
bell/res/webapp/templates/series.html