Metadata-Version: 1.1
Name: bell
Version: 0.5.6
Summary: Realtime anomalies detection based on statsd, for periodic time series.
Home-page: https://github.com/eleme/bell
Author: hit9
Author-email: wangchao@ele.me
License: MIT
Keywords: anomaly outlier timeseries metric statsd
Platform: UNKNOWN
Classifier: Development Status :: 2 - Pre-Alpha
Classifier: Environment :: Console
Classifier: Intended Audience :: Customer Service
Classifier: License :: OSI Approved :: MIT License
Classifier: Operating System :: POSIX
Classifier: Programming Language :: Python
Classifier: Programming Language :: Python :: 2.7
